conditions_py/__init__.py
conditions_py/condition.py
conditions_py/errors/__init__.py
conditions_py/errors/argument_error.py
conditions_py/errors/argument_null_error.py
conditions_py/errors/argument_out_of_range_error.py
conditions_py/errors/argument_pattern_error.py
conditions_py/helpers/__init__.py
conditions_py/helpers/regex_helper.py
conditions_py/validators/__init__.py
conditions_py/validators/boolean_validator.py
conditions_py/validators/number_validator.py
conditions_py/validators/object_validator.py
conditions_py/validators/string_validator.py
conditions_py/validators/validator.py
conditions_py-0.1.3.dist-info/LICENSE
conditions_py-0.1.3.dist-info/METADATA
conditions_py-0.1.3.dist-info/WHEEL
conditions_py-0.1.3.dist-info/top_level.txt
conditions_py-0.1.3.dist-info/RECORD
