Metadata-Version: 2.1
Name: conditions-py
Version: 0.1.3
Summary: conditions-py is a library that helps write pre- and postcondition validations in a fluent manner, helping improve the readability and reliability of code.
Home-page: https://github.com/GenesisCoast/conditions-py
Author: Harry Sanderson
Author-email: harrysanderson@hotmail.co.uk
License: MIT
Platform: UNKNOWN
Classifier: Development Status :: 4 - Beta
Classifier: Intended Audience :: Developers
Classifier: License :: OSI Approved :: MIT License
Classifier: Natural Language :: English
Classifier: Programming Language :: Python :: 3
Classifier: Programming Language :: Python :: 3.5
Classifier: Programming Language :: Python :: 3.6
Classifier: Programming Language :: Python :: 3.7
Classifier: Programming Language :: Python :: Implementation :: CPython
